stac_fastapi/core/__init__.py
stac_fastapi/core/base_database_logic.py
stac_fastapi/core/base_settings.py
stac_fastapi/core/basic_auth.py
stac_fastapi/core/core.py
stac_fastapi/core/datetime_utils.py
stac_fastapi/core/queryables.py
stac_fastapi/core/rate_limit.py
stac_fastapi/core/redis_utils.py
stac_fastapi/core/route_dependencies.py
stac_fastapi/core/serializers.py
stac_fastapi/core/session.py
stac_fastapi/core/utilities.py
stac_fastapi/core/version.py
stac_fastapi/core/extensions/__init__.py
stac_fastapi/core/extensions/aggregation.py
stac_fastapi/core/extensions/catalogs.py
stac_fastapi/core/extensions/collections_search.py
stac_fastapi/core/extensions/fields.py
stac_fastapi/core/extensions/filter.py
stac_fastapi/core/extensions/query.py
stac_fastapi/core/models/__init__.py
stac_fastapi/core/models/links.py
stac_fastapi/core/models/search.py
stac_fastapi_core-6.10.0.dist-info/METADATA
stac_fastapi_core-6.10.0.dist-info/WHEEL
stac_fastapi_core-6.10.0.dist-info/RECORD
